pyrgelis/__init__.py
pyrgelis/cli.py
pyrgelis/game.py
pyrgelis/rgeli.py
pyrgelis-0.1.1.dist-info/LICENSE
pyrgelis-0.1.1.dist-info/METADATA
pyrgelis-0.1.1.dist-info/WHEEL
pyrgelis-0.1.1.dist-info/entry_points.txt
pyrgelis-0.1.1.dist-info/top_level.txt
pyrgelis-0.1.1.dist-info/RECORD
