Metadata-Version: 2.2
Name: pyrgelis
Version: 0.1.1
Summary: Rgelis floating in a surreal space. You can only win.
Home-page: https://github.com/username/pyrgelis
Author: Vasilios Mavroudis
Author-email: mavroudisv@gmail.com
Classifier: Programming Language :: Python :: 3
Classifier: License :: OSI Approved :: MIT License
Classifier: Operating System :: OS Independent
Classifier: Topic :: Games/Entertainment :: Simulation
Classifier: Topic :: Artistic Software
Requires-Python: >=3.6
License-File: LICENSE
Requires-Dist: numpy>=1.19.0
Requires-Dist: matplotlib>=3.3.0
Dynamic: author
Dynamic: author-email
Dynamic: classifier
Dynamic: description
Dynamic: description-content-type
Dynamic: home-page
Dynamic: requires-dist
Dynamic: requires-python
Dynamic: summary
